peracotta/__init__.py
peracotta/commons.py
peracotta/config.py
peracotta/config.toml
peracotta/constants.py
peracotta/crash_reporting.py
peracotta/features.json
peracotta/peracruda.py
peracotta/peralog.py
peracotta/tarallo.py
peracotta/assets/Installing.gif
peracotta/assets/error.ui
peracotta/assets/interface.ui
peracotta/assets/uploadTaralloDialog.ui
peracotta/assets/themes/Dark.css
peracotta/assets/themes/WEEE Open.css
peracotta/assets/themes/default.css
peracotta/assets/toolbox/case.png
peracotta/assets/toolbox/cpu.png
peracotta/assets/toolbox/gpu.png
peracotta/assets/toolbox/hdd.png
peracotta/assets/toolbox/keyboard.png
peracotta/assets/toolbox/monitor.png
peracotta/assets/toolbox/motherboard.png
peracotta/assets/toolbox/mouse.png
peracotta/assets/toolbox/odd.png
peracotta/assets/toolbox/psu.png
peracotta/assets/toolbox/ram.png
peracotta/assets/toolbox/ssd.png
peracotta/assets/toolbox/wifi-card.png
peracotta/assets/ui/light_down_arrow.png
peracotta/assets/ui/light_split_handle.png
peracotta/assets/ui/pear_emoji.png
peracotta/assets/ui/radio_ckd.png
peracotta/assets/ui/radio_unckd.png
peracotta/gui/PeraThread.py
peracotta/gui/Toolbox.py
peracotta/gui/__init__.py
peracotta/gui/exception_handler.py
peracotta/gui/exceptions.py
peracotta/gui/gui.py
peracotta/gui/prettyprinter.py
peracotta/gui/widgets.py
peracotta/parsers/__init__.py
peracotta/parsers/read_decode_dimms.py
peracotta/parsers/read_dmidecode.py
peracotta/parsers/read_lscpu.py
peracotta/parsers/read_lspci_and_glxinfo.py
peracotta/parsers/read_smartctl.py
peracotta/parsers/read_udevadm.py
peracotta/parsers/windows_parser.py
peracotta/scripts/check_dependencies.sh
peracotta/scripts/generate_files.sh
peracotta/scripts/get_windows_specs.py
peracotta/scripts/install_dependencies_all.sh
peracotta-2.5.10.dist-info/licenses/LICENSE
peracotta-2.5.10.dist-info/METADATA
peracotta-2.5.10.dist-info/WHEEL
peracotta-2.5.10.dist-info/entry_points.txt
peracotta-2.5.10.dist-info/top_level.txt
peracotta-2.5.10.dist-info/RECORD
