Metadata-Version: 2.4
Name: peracotta
Version: 2.5.10
Classifier: Development Status :: 4 - Beta
Classifier: Programming Language :: Python :: 3.9
Classifier: Programming Language :: Python :: 3.10
Classifier: Programming Language :: Python :: 3.11
Classifier: Programming Language :: Python :: 3.12
Classifier: Environment :: X11 Applications :: Qt
Requires-Python: >=3.9
License-File: LICENSE
Requires-Dist: PyQt5
Requires-Dist: pytarallo
Requires-Dist: python-dotenv
Requires-Dist: requests
Requires-Dist: typing-extensions
Requires-Dist: urllib3
Requires-Dist: importlib_resources
Requires-Dist: loguru
Requires-Dist: rich
Requires-Dist: requests
Requires-Dist: toml
Dynamic: license-file
